LICENSE
MANIFEST.in
README.md
setup.py
debtools/__init__.py
debtools/__init__.pyc
debtools/aptenv.py
debtools/aptenv.pyc
debtools/ar.py
debtools/ar.pyc
debtools/debdeptree.py
debtools/multideb.py
debtools/utils.py
debtools/utils.pyc
debtools.egg-info/PKG-INFO
debtools.egg-info/SOURCES.txt
debtools.egg-info/dependency_links.txt
debtools.egg-info/entry_points.txt
debtools.egg-info/not-zip-safe
debtools.egg-info/requires.txt
debtools.egg-info/top_level.txt
debtools/__pycache__/__init__.cpython-34.pyc
debtools/__pycache__/__init__.cpython-35.pyc
debtools/__pycache__/aptenv.cpython-35.pyc
debtools/__pycache__/ar.cpython-34.pyc
debtools/__pycache__/debdeptree.cpython-34.pyc
debtools/__pycache__/multideb.cpython-34.pyc
debtools/__pycache__/utils.cpython-34.pyc
debtools/tests/__init__.py
debtools/tests/__init__.pyc
debtools/tests/packages.debian.org.html
debtools/tests/python-debtools_0.3-1_all.deb
debtools/tests/tests_utils.py
debtools/tests/tests_utils.pyc