Metadata-Version: 1.0
Name: debtools
Version: 0.7.4
Summary: Utilities for creating mutliple Debian packages.
Home-page: https://github.com/d9pouces/DebTools
Author: Matthieu Gallet
Author-email: gallet.matthieu@19pouces.net
License: CeCILL-B
Platform: UNKNOWN
